Workbook

Sheet Task Notes
A1: Set 18 - SampleSuperstore: clean, pivot, conditional format, dashboard, top 5
A2: Each task has its own worksheet (named in the 'Worksheet' column). Sample data is synthetic and created for this assignment.
A4: Task | B4: Question (summary) | C4: Worksheet | D4: What was done / answer / explanation
A5: 1 | B5: Clean SampleSuperstore.csv so each Order ID appears once. | C5: SampleSuperstore_Raw / T1_Cleaned | D5: The standard Kaggle SampleSuperstore.csv has no Order ID column, so this assignment file adds one (synthetic data in the same layout; file SampleSuperstore.csv). Raw: 340 rows with repeated Order IDs. Cleaned: Data > Remove Duplicates on the Order ID column only (or Advanced Filter > Unique records only) keeps the first line per order = 300 rows. Check cells Q1:Q3 on T1_Cleaned.
A6: 2 | B6: Pivot table of Sales and Profit by Region; highlight highest profit. | C6: T2_Region / T2_Pivot | D6: Real PivotTable on T2_Pivot (Region in Rows; Sum of Sales and Sum of Profit). T2_Region reproduces it with SUMIFS and highlights the highest-profit region with conditional formatting (formula =$C2=MAX($C$2:$C$5)). Highest profit in this data: Central.
A7: 3 | B7: Conditional formatting: Discount > 20% and Profit negative. | C7: T3_Highlight | D7: Rule on A2:N301: =AND($M2>0.2,$N2<0) with light-red fill. 39 of 300 orders are highlighted (Q1:Q2 count them with COUNTIFS).
A8: 4 | B8: Dashboard: total Sales, total Profit and bar chart of Sales by Category. | C8: T4_Dashboard | D8: KPI cards use SUM formulas and the chart reads a SUMIFS category table. Snapshot: Set18_Dashboard.jpg.
A9: 5 | B9: Quick Analysis / Recommended Charts: top 5 profitable Sub-Categories with a comment. | C9: T5_Top5_SubCategory | D9: LARGE + INDEX/MATCH pick the 5 most profitable sub-categories (dynamic), shown in a bar chart; the findings are written in the yellow comment box (also attached as a cell comment on F1).

Sheet SampleSuperstore_Raw
A1: Order ID | B1: Ship Mode | C1: Segment | D1: Country | E1: City | F1: State | G1: Postal Code | H1: Region | I1: Category | J1: Sub-Category | K1: Sales | L1: Quantity | M1: Discount | N1: Profit
A2: CA-2026-100053 | B2: Standard Class | C2: Corporate | D2: United States | E2: New York City | F2: New York | G2: 10011 | H2: East | I2: Furniture | J2: Chairs | K2: 143.63 | L2: 4 | M2: 0.1 | N2: 3.49
A3: CA-2026-100141 | B3: Standard Class | C3: Home Office | D3: United States | E3: Nashville | F3: Tennessee | G3: 37211 | H3: South | I3: Technology | J3: Machines | K3: 50 | L3: 4 | M3: 0 | N3: 11.09
A4: CA-2026-100209 | B4: Same Day | C4: Home Office | D4: United States | E4: Atlanta | F4: Georgia | G4: 30318 | H4: South | I4: Furniture | J4: Furnishings | K4: 29.74 | L4: 9 | M4: 0.15 | N4: 1.21
A5: CA-2026-100213 | B5: Standard Class | C5: Corporate | D5: United States | E5: Houston | F5: Texas | G5: 77095 | H5: Central | I5: Office Supplies | J5: Art | K5: 137.48 | L5: 1 | M5: 0 | N5: 43.59
A6: CA-2026-100295 | B6: Second Class | C6: Consumer | D6: United States | E6: Denver | F6: Colorado | G6: 80219 | H6: West | I6: Technology | J6: Phones | K6: 54.35 | L6: 2 | M6: 0.7 | N6: 1.26
A7: CA-2026-100061 | B7: Same Day | C7: Consumer | D7: United States | E7: Chicago | F7: Illinois | G7: 60610 | H7: Central | I7: Technology | J7: Accessories | K7: 99.88 | L7: 1 | M7: 0.4 | N7: 29.44
A8: CA-2026-100194 | B8: Standard Class | C8: Corporate | D8: United States | E8: Boston | F8: Massachusetts | G8: 2127 | H8: East | I8: Office Supplies | J8: Envelopes | K8: 41.95 | L8: 9 | M8: 0 | N8: 11.74
A9: CA-2026-100216 | B9: First Class | C9: Consumer | D9: United States | E9: Denver | F9: Colorado | G9: 80219 | H9: West | I9: Furniture | J9: Tables | K9: 34.19 | L9: 5 | M9: 0.2 | N9: -4.59
A10: CA-2026-100128 | B10: Second Class | C10: Home Office | D10: United States | E10: Denver | F10: Colorado | G10: 80219 | H10: West | I10: Furniture | J10: Bookcases | K10: 206.18 | L10: 6 | M10: 0 | N10: 11.43
A11: CA-2026-100142 | B11: Second Class | C11: Consumer | D11: United States | E11: New York City | F11: New York | G11: 10011 | H11: East | I11: Office Supplies | J11: Storage | K11: 137.56 | L11: 9 | M11: 0 | N11: 52.23
A12: CA-2026-100118 | B12: First Class | C12: Corporate | D12: United States | E12: Houston | F12: Texas | G12: 77095 | H12: Central | I12: Furniture | J12: Chairs | K12: 182.97 | L12: 8 | M12: 0 | N12: 25.84
A13: CA-2026-100064 | B13: Same Day | C13: Consumer | D13: United States | E13: Miami | F13: Florida | G13: 33311 | H13: South | I13: Technology | J13: Copiers | K13: 53.73 | L13: 8 | M13: 0 | N13: 23.81
... A341: CA-2026-100115 | B341: Second Class | C341: Home Office | D341: United States | E341: Boston | F341: Massachusetts | G341: 2127 | H341: East | I341: Technology | J341: Machines | K341: 88.44 | L341: 3 | M341: 0 | N341: 27.63

Sheet T1_Cleaned
A1: Order ID | B1: Ship Mode | C1: Segment | D1: Country | E1: City | F1: State | G1: Postal Code | H1: Region | I1: Category | J1: Sub-Category | K1: Sales | L1: Quantity | M1: Discount | N1: Profit | P1: Rows before | Q1: =COUNTA(SampleSuperstore_Raw!A2:A341) -> 340
A2: CA-2026-100001 | B2: Second Class | C2: Corporate | D2: United States | E2: New York City | F2: New York | G2: 10011 | H2: East | I2: Technology | J2: Phones | K2: 108.53 | L2: 5 | M2: 0.2 | N2: 30.01 | P2: Rows after | Q2: =COUNTA(A2:A301) -> 300
A3: CA-2026-100002 | B3: Second Class | C3: Consumer | D3: United States | E3: Charlotte | F3: North Carolina | G3: 28205 | H3: South | I3: Furniture | J3: Furnishings | K3: 114.86 | L3: 4 | M3: 0 | N3: 22.81 | P3: Duplicate Order IDs left | Q3: =SUMPRODUCT(--(COUNTIF(A2:A301,A2:A301)>1)) -> 0
A4: CA-2026-100003 | B4: Standard Class | C4: Corporate | D4: United States | E4: Boston | F4: Massachusetts | G4: 2127 | H4: East | I4: Technology | J4: Copiers | K4: 325.84 | L4: 7 | M4: 0.7 | N4: 11.02
A5: CA-2026-100004 | B5: First Class | C5: Home Office | D5: United States | E5: Newark | F5: New Jersey | G5: 7102 | H5: East | I5: Technology | J5: Machines | K5: 202.43 | L5: 2 | M5: 0.1 | N5: 67.61
A6: CA-2026-100005 | B6: Same Day | C6: Consumer | D6: United States | E6: Minneapolis | F6: Minnesota | G6: 55407 | H6: Central | I6: Technology | J6: Phones | K6: 177.32 | L6: 7 | M6: 0 | N6: -39.06
A7: CA-2026-100006 | B7: Same Day | C7: Consumer | D7: United States | E7: Miami | F7: Florida | G7: 33311 | H7: South | I7: Technology | J7: Copiers | K7: 200.02 | L7: 8 | M7: 0.15 | N7: 90.71
A8: CA-2026-100007 | B8: Standard Class | C8: Consumer | D8: United States | E8: Newark | F8: New Jersey | G8: 7102 | H8: East | I8: Furniture | J8: Tables | K8: 108.24 | L8: 2 | M8: 0.5 | N8: -33.24
A9: CA-2026-100008 | B9: First Class | C9: Consumer | D9: United States | E9: Nashville | F9: Tennessee | G9: 37211 | H9: South | I9: Office Supplies | J9: Binders | K9: 44.65 | L9: 6 | M9: 0.7 | N9: -6.72
A10: CA-2026-100009 | B10: Same Day | C10: Consumer | D10: United States | E10: Dallas | F10: Texas | G10: 75217 | H10: Central | I10: Furniture | J10: Tables | K10: 51.79 | L10: 9 | M10: 0.7 | N10: -18.89
A11: CA-2026-100010 | B11: Same Day | C11: Consumer | D11: United States | E11: Miami | F11: Florida | G11: 33311 | H11: South | I11: Furniture | J11: Furnishings | K11: 81.28 | L11: 4 | M11: 0.4 | N11: -8.02
A12: CA-2026-100011 | B12: Second Class | C12: Home Office | D12: United States | E12: Philadelphia | F12: Pennsylvania | G12: 19140 | H12: East | I12: Office Supplies | J12: Fasteners | K12: 53.1 | L12: 3 | M12: 0 | N12: 19.58
A13: CA-2026-100012 | B13: First Class | C13: Consumer | D13: United States | E13: Boston | F13: Massachusetts | G13: 2127 | H13: East | I13: Furniture | J13: Chairs | K13: 566.33 | L13: 6 | M13: 0 | N13: 45.79
A14: CA-2026-100013 | B14: Same Day | C14: Home Office | D14: United States | E14: Portland | F14: Oregon | G14: 97206 | H14: West | I14: Office Supplies | J14: Art | K14: 678.03 | L14: 7 | M14: 0.7 | N14: -126.57
A15: CA-2026-100014 | B15: Second Class | C15: Corporate | D15: United States | E15: Portland | F15: Oregon | G15: 97206 | H15: West | I15: Office Supplies | J15: Appliances | K15: 64.73 | L15: 3 | M15: 0 | N15: 16.47
... A301: CA-2026-100300 | B301: Same Day | C301: Corporate | D301: United States | E301: Los Angeles | F301: California | G301: 90036 | H301: West | I301: Furniture | J301: Tables | K301: 150.2 | L301: 9 | M301: 0.2 | N301: -16.73

Sheet T2_Region
A1: Region | B1: Total Sales | C1: Total Profit | D1: Profit Margin
A2: Central | B2: =SUMIFS(T1_Cleaned!$K$2:$K$301,T1_Cleaned!$H$2:$H$301,A2) -> 13023.56 | C2: =SUMIFS(T1_Cleaned!$N$2:$N$301,T1_Cleaned!$H$2:$H$301,A2) -> 1645.23 | D2: =C2/B2 -> 0.12632721
A3: East | B3: =SUMIFS(T1_Cleaned!$K$2:$K$301,T1_Cleaned!$H$2:$H$301,A3) -> 9921.97 | C3: =SUMIFS(T1_Cleaned!$N$2:$N$301,T1_Cleaned!$H$2:$H$301,A3) -> 1409.08 | D3: =C3/B3 -> 0.14201615
A4: South | B4: =SUMIFS(T1_Cleaned!$K$2:$K$301,T1_Cleaned!$H$2:$H$301,A4) -> 16879.42 | C4: =SUMIFS(T1_Cleaned!$N$2:$N$301,T1_Cleaned!$H$2:$H$301,A4) -> -1240.82 | D4: =C4/B4 -> -0.07351082
A5: West | B5: =SUMIFS(T1_Cleaned!$K$2:$K$301,T1_Cleaned!$H$2:$H$301,A5) -> 13387.39 | C5: =SUMIFS(T1_Cleaned!$N$2:$N$301,T1_Cleaned!$H$2:$H$301,A5) -> 1632.33 | D5: =C5/B5 -> 0.12193041
A6: Total | B6: =SUM(B2:B5) -> 53212.34 | C6: =SUM(C2:C5) -> 3445.82 | D6: =C6/B6 -> 0.064756032
A8: ="Highest-profit region: "&INDEX(A2:A5,MATCH(MAX(C2:C5),C2:C5,0))&" ($ "&TEXT(MAX(C2:C5),"#,##0")&")" -> Highest-profit region: Central ($ 1,645)

Sheet T3_Highlight
A1: Order ID | B1: Ship Mode | C1: Segment | D1: Country | E1: City | F1: State | G1: Postal Code | H1: Region | I1: Category | J1: Sub-Category | K1: Sales | L1: Quantity | M1: Discount | N1: Profit | P1: Rows with Discount > 20% AND Profit < 0 | Q1: =COUNTIFS(M2:M301,">0.2",N2:N301,"<0") -> 39
A2: CA-2026-100001 | B2: Second Class | C2: Corporate | D2: United States | E2: New York City | F2: New York | G2: 10011 | H2: East | I2: Technology | J2: Phones | K2: 108.53 | L2: 5 | M2: 0.2 | N2: 30.01 | P2: Share of all orders | Q2: =Q1/COUNTA(A2:A301) -> 0.13
A3: CA-2026-100002 | B3: Second Class | C3: Consumer | D3: United States | E3: Charlotte | F3: North Carolina | G3: 28205 | H3: South | I3: Furniture | J3: Furnishings | K3: 114.86 | L3: 4 | M3: 0 | N3: 22.81
A4: CA-2026-100003 | B4: Standard Class | C4: Corporate | D4: United States | E4: Boston | F4: Massachusetts | G4: 2127 | H4: East | I4: Technology | J4: Copiers | K4: 325.84 | L4: 7 | M4: 0.7 | N4: 11.02
A5: CA-2026-100004 | B5: First Class | C5: Home Office | D5: United States | E5: Newark | F5: New Jersey | G5: 7102 | H5: East | I5: Technology | J5: Machines | K5: 202.43 | L5: 2 | M5: 0.1 | N5: 67.61
A6: CA-2026-100005 | B6: Same Day | C6: Consumer | D6: United States | E6: Minneapolis | F6: Minnesota | G6: 55407 | H6: Central | I6: Technology | J6: Phones | K6: 177.32 | L6: 7 | M6: 0 | N6: -39.06
A7: CA-2026-100006 | B7: Same Day | C7: Consumer | D7: United States | E7: Miami | F7: Florida | G7: 33311 | H7: South | I7: Technology | J7: Copiers | K7: 200.02 | L7: 8 | M7: 0.15 | N7: 90.71
A8: CA-2026-100007 | B8: Standard Class | C8: Consumer | D8: United States | E8: Newark | F8: New Jersey | G8: 7102 | H8: East | I8: Furniture | J8: Tables | K8: 108.24 | L8: 2 | M8: 0.5 | N8: -33.24
A9: CA-2026-100008 | B9: First Class | C9: Consumer | D9: United States | E9: Nashville | F9: Tennessee | G9: 37211 | H9: South | I9: Office Supplies | J9: Binders | K9: 44.65 | L9: 6 | M9: 0.7 | N9: -6.72
A10: CA-2026-100009 | B10: Same Day | C10: Consumer | D10: United States | E10: Dallas | F10: Texas | G10: 75217 | H10: Central | I10: Furniture | J10: Tables | K10: 51.79 | L10: 9 | M10: 0.7 | N10: -18.89
A11: CA-2026-100010 | B11: Same Day | C11: Consumer | D11: United States | E11: Miami | F11: Florida | G11: 33311 | H11: South | I11: Furniture | J11: Furnishings | K11: 81.28 | L11: 4 | M11: 0.4 | N11: -8.02
A12: CA-2026-100011 | B12: Second Class | C12: Home Office | D12: United States | E12: Philadelphia | F12: Pennsylvania | G12: 19140 | H12: East | I12: Office Supplies | J12: Fasteners | K12: 53.1 | L12: 3 | M12: 0 | N12: 19.58
A13: CA-2026-100012 | B13: First Class | C13: Consumer | D13: United States | E13: Boston | F13: Massachusetts | G13: 2127 | H13: East | I13: Furniture | J13: Chairs | K13: 566.33 | L13: 6 | M13: 0 | N13: 45.79
A14: CA-2026-100013 | B14: Same Day | C14: Home Office | D14: United States | E14: Portland | F14: Oregon | G14: 97206 | H14: West | I14: Office Supplies | J14: Art | K14: 678.03 | L14: 7 | M14: 0.7 | N14: -126.57
... A301: CA-2026-100300 | B301: Same Day | C301: Corporate | D301: United States | E301: Los Angeles | F301: California | G301: 90036 | H301: West | I301: Furniture | J301: Tables | K301: 150.2 | L301: 9 | M301: 0.2 | N301: -16.73

Sheet T4_Dashboard
B1: SUPERSTORE SALES DASHBOARD
B4: TOTAL SALES | E4: TOTAL PROFIT | H4: ORDERS
B5: =SUM(T1_Cleaned!$K$2:$K$301) -> 53212.34 | E5: =SUM(T1_Cleaned!$N$2:$N$301) -> 3445.82 | H5: =COUNTA(T1_Cleaned!$A$2:$A$301) -> 300
B24: Sales by Category (feeds chart)
B25: Category | C25: Total Sales | D25: Order lines
B26: Furniture | C26: =SUMIFS(T1_Cleaned!$K$2:$K$301,T1_Cleaned!$I$2:$I$301,B26) -> 17864.39 | D26: =COUNTIFS(T1_Cleaned!$I$2:$I$301,B26) -> 91
B27: Office Supplies | C27: =SUMIFS(T1_Cleaned!$K$2:$K$301,T1_Cleaned!$I$2:$I$301,B27) -> 8329.17 | D27: =COUNTIFS(T1_Cleaned!$I$2:$I$301,B27) -> 107
B28: Technology | C28: =SUMIFS(T1_Cleaned!$K$2:$K$301,T1_Cleaned!$I$2:$I$301,B28) -> 27018.78 | D28: =COUNTIFS(T1_Cleaned!$I$2:$I$301,B28) -> 102

Sheet T5_Top5_SubCategory
A1: Sub-Category | B1: Total Profit | D1: Rank | E1: Sub-Category | F1: Total Profit
A2: Accessories | B2: =SUMIFS(T1_Cleaned!$N$2:$N$301,T1_Cleaned!$J$2:$J$301,A2) -> 1143.28 | D2: 1 | E2: =INDEX($A$2:$A$18,MATCH(F2,$B$2:$B$18,0)) -> Machines | F2: =LARGE($B$2:$B$18,D2) -> 1654.95
A3: Appliances | B3: =SUMIFS(T1_Cleaned!$N$2:$N$301,T1_Cleaned!$J$2:$J$301,A3) -> 293.4 | D3: 2 | E3: =INDEX($A$2:$A$18,MATCH(F3,$B$2:$B$18,0)) -> Accessories | F3: =LARGE($B$2:$B$18,D3) -> 1143.28
A4: Art | B4: =SUMIFS(T1_Cleaned!$N$2:$N$301,T1_Cleaned!$J$2:$J$301,A4) -> -17.62 | D4: 3 | E4: =INDEX($A$2:$A$18,MATCH(F4,$B$2:$B$18,0)) -> Phones | F4: =LARGE($B$2:$B$18,D4) -> 580.33
A5: Binders | B5: =SUMIFS(T1_Cleaned!$N$2:$N$301,T1_Cleaned!$J$2:$J$301,A5) -> 99.39 | D5: 4 | E5: =INDEX($A$2:$A$18,MATCH(F5,$B$2:$B$18,0)) -> Paper | F5: =LARGE($B$2:$B$18,D5) -> 372.82
A6: Bookcases | B6: =SUMIFS(T1_Cleaned!$N$2:$N$301,T1_Cleaned!$J$2:$J$301,A6) -> -595.34 | D6: 5 | E6: =INDEX($A$2:$A$18,MATCH(F6,$B$2:$B$18,0)) -> Appliances | F6: =LARGE($B$2:$B$18,D6) -> 293.4
A7: Chairs | B7: =SUMIFS(T1_Cleaned!$N$2:$N$301,T1_Cleaned!$J$2:$J$301,A7) -> 252.22
A8: Copiers | B8: =SUMIFS(T1_Cleaned!$N$2:$N$301,T1_Cleaned!$J$2:$J$301,A8) -> -692.74
A9: Envelopes | B9: =SUMIFS(T1_Cleaned!$N$2:$N$301,T1_Cleaned!$J$2:$J$301,A9) -> 134.18
A10: Fasteners | B10: =SUMIFS(T1_Cleaned!$N$2:$N$301,T1_Cleaned!$J$2:$J$301,A10) -> 142.53
A11: Furnishings | B11: =SUMIFS(T1_Cleaned!$N$2:$N$301,T1_Cleaned!$J$2:$J$301,A11) -> -95.46
A12: Labels | B12: =SUMIFS(T1_Cleaned!$N$2:$N$301,T1_Cleaned!$J$2:$J$301,A12) -> 109.78
A13: Machines | B13: =SUMIFS(T1_Cleaned!$N$2:$N$301,T1_Cleaned!$J$2:$J$301,A13) -> 1654.95
A14: Paper | B14: =SUMIFS(T1_Cleaned!$N$2:$N$301,T1_Cleaned!$J$2:$J$301,A14) -> 372.82
A15: Phones | B15: =SUMIFS(T1_Cleaned!$N$2:$N$301,T1_Cleaned!$J$2:$J$301,A15) -> 580.33
A16: Storage | B16: =SUMIFS(T1_Cleaned!$N$2:$N$301,T1_Cleaned!$J$2:$J$301,A16) -> 133.73
A17: Supplies | B17: =SUMIFS(T1_Cleaned!$N$2:$N$301,T1_Cleaned!$J$2:$J$301,A17) -> 135.87
A18: Tables | B18: =SUMIFS(T1_Cleaned!$N$2:$N$301,T1_Cleaned!$J$2:$J$301,A18) -> -205.5
D26: Findings
D27: Findings (sample data): top 5 sub-categories by profit are Machines (1,655), Accessories (1,143), Phones (580), Paper (373), Appliances (293). Heavily discounted lines (discount > 20%) drive the losses highlighted on sheet T3_Highlight, so discount control is the main profit lever.

Sheet T2_Pivot
A2: Filter
A4: Region | B4: Data
A5: Central | B5: Sum - Sales | C5: 13023.56
B6: Sum - Profit | C6: 1645.23
A7: East | B7: Sum - Sales | C7: 9921.97
B8: Sum - Profit | C8: 1409.08
A9: South | B9: Sum - Sales | C9: 16879.42
B10: Sum - Profit | C10: -1240.82
A11: West | B11: Sum - Sales | C11: 13387.39
B12: Sum - Profit | C12: 1632.33
A13: Total Sum - Sales | C13: 53212.34
A14: Total Sum - Profit | C14: 3445.82
